bruce/__init__.py
bruce/binarystar/__init__.py
bruce/binarystar/brent.py
bruce/binarystar/doppler.py
bruce/binarystar/eker_spots.py
bruce/binarystar/ellipsoidal.py
bruce/binarystar/flux_drop.py
bruce/binarystar/kepler.py
bruce/binarystar/lc.py
bruce/binarystar/qpower2.py
bruce/binarystar/quadratic.py
bruce/binarystar/reflection.py
bruce/binarystar/rm.py
bruce/binarystar/rv.py
bruce/binarystar/uniform.py
bruce_package-3.7.data/scripts/PAOtls
bruce_package-3.7.data/scripts/analyse
bruce_package-3.7.data/scripts/aperturesearch
bruce_package-3.7.data/scripts/findtransit
bruce_package-3.7.data/scripts/fitpipe
bruce_package-3.7.data/scripts/lcbin
bruce_package-3.7.data/scripts/massfunc
bruce_package-3.7.data/scripts/mbls
bruce_package-3.7.data/scripts/modulation
bruce_package-3.7.data/scripts/ngtsfit
bruce_package-3.7.data/scripts/plot_nights
bruce_package-3.7.data/scripts/predict
bruce_package-3.7.data/scripts/predictedges
bruce_package-3.7.data/scripts/prepare
bruce_package-3.7.data/scripts/prewhiten
bruce_package-3.7.data/scripts/quickphot
bruce_package-3.7.data/scripts/quickphotcube
bruce_package-3.7.data/scripts/templatematch
bruce_package-3.7.data/scripts/tessget
bruce_package-3.7.data/scripts/tessgetpca
bruce_package-3.7.data/scripts/tessquery
bruce_package-3.7.data/scripts/tic2wasp
bruce_package-3.7.data/scripts/tls
bruce_package-3.7.dist-info/METADATA
bruce_package-3.7.dist-info/WHEEL
bruce_package-3.7.dist-info/top_level.txt
bruce_package-3.7.dist-info/RECORD
