Metadata-Version: 2.1
Name: bruce-package
Version: 3.7
Summary: GPU-accelerated binary star model
Home-page: UNKNOWN
Author: Samuel Gill et al
Author-email: samuel.gill@warwick.ac.uk
License: GNU
Platform: UNKNOWN
Requires-Dist: numba
